etcher/__init__.py
etcher/db.py
etcher/exceptions.py
etcher/sqlitedis.py
etcher-0.1.3.dist-info/licenses/LICENSE
etcher-0.1.3.dist-info/METADATA
etcher-0.1.3.dist-info/WHEEL
etcher-0.1.3.dist-info/top_level.txt
etcher-0.1.3.dist-info/RECORD
