Metadata-Version: 2.4
Name: etcher
Version: 0.1.3
Summary: Persistent Python dict/list containers (RD/RL) with automatic backreferences, transactions, and GC over a Redis-like KV store. Default SQLite backend; optional redislite/Redis.
Author-email: Chris Bates <1314008+chrsbats@users.noreply.github.com>
License-Expression: MIT
Classifier: Programming Language :: Python :: 3
Classifier: Programming Language :: Python :: 3 :: Only
Classifier: Programming Language :: Python :: 3.9
Classifier: Programming Language :: Python :: 3.10
Classifier: Programming Language :: Python :: 3.11
Classifier: Programming Language :: Python :: 3.12
Classifier: Programming Language :: Python :: 3.13
Classifier: Operating System :: OS Independent
Requires-Python: >=3.9
License-File: LICENSE
Requires-Dist: python-ulid<4,>=3
Provides-Extra: dev
Requires-Dist: pytest>=8.0.0; extra == "dev"
Requires-Dist: pytest-cov>=5.0.0; extra == "dev"
Requires-Dist: pytest-asyncio>=0.23.0; extra == "dev"
Requires-Dist: pytest-benchmark>=4.0.0; extra == "dev"
Requires-Dist: pytest-mock>=3.14.0; extra == "dev"
Requires-Dist: anyio>=4.0.0; extra == "dev"
Requires-Dist: flake8>=7.0.0; extra == "dev"
Provides-Extra: redislite
Requires-Dist: redislite<7,>=6.2; extra == "redislite"
Requires-Dist: redis<6,>=4; extra == "redislite"
Provides-Extra: redis
Requires-Dist: redis<6,>=4; extra == "redis"
Dynamic: license-file
